[
    {
        "title": "Кавун Леді",
        "price":  40,
        "image": "img/кавун1.webp",
        "description": "Мякоть яскраво-червона, ніжної структури, солодка, хрустка, без волокон."
    },
    {
        "title": "Кавун Красень",
        "price":  50,
        "image": "img/5.jpg",
        "description": "Мякуш Яскрава-червоного кольору, зерниста, ніжний,Соковита та солодкий. Смакові якості відмінні."
    },
    {
        "title": "Оранж Кінг F1",
        "price":  60,
        "image": "img/6.jpeg",
        "description": "Мякоть яскраво-жовта, ніжна, без прожилок і пирот, дуже солодка та соковита."
    },
    {
        "title": "Кавун Шуга Єллоу F1",
        "price":  65,
        "image": "img/7.jpeg",
        "description": "Мякоть сладка та сочна, упруга й ароматна."
    },
    {
        "title": "Чарльстон Грей",
        "price":  50,
        "image": "img/8.jpg",
        "description": "Сорт привертає яскраво-рожевою соковитою мякоттю, деякі екземпляри кавунів важать 12-15 кілограмів."
    },
    {
        "title": "Кавун Сніжок",
        "price":  60,
        "image": "img/9.jpg",
        "description": " Мякоть яскравого червоного або темно-рожевого кольору, зерниста, дуже солодка і соковита."
    }
]